rustrees-0.2.4.dist-info/METADATA
rustrees-0.2.4.dist-info/WHEEL
rustrees/decision_tree.py
rustrees/__init__.py
rustrees/utils.py
rustrees/random_forest.py
rustrees/rustrees.cpython-311-aarch64-linux-gnu.so
rustrees-0.2.4.dist-info/RECORD
