Metadata-Version: 2.1
Name: rustrees
Version: 0.2.4
Requires-Dist: numpy >=1.0
Requires-Dist: pandas >=2.0
Requires-Dist: scikit-learn >=1.0
Requires-Dist: pyarrow >=12.0
Summary: Decision trees in Rust
Keywords: machine-learning,decision-trees,python
Author: Guilherme Lázari <guilhermelcs@gmail.com>, Pedro Tabacof <tabacof@gmail.com>
Author-email: Guilherme Lázari <guilhermelcs@gmail.com>, Pedro Tabacof <tabacof@gmail.com>
License: MIT
Project-URL: homepage, https://github.com/tabacof/rust-trees
Project-URL: documentation, https://rust-trees.readthedocs.io/en/latest/
Project-URL: rust, https://crates.io/crates/rustrees
